.editorconfig
.env
.gitignore
LICENSE
MANIFEST.in
Pipfile
Pipfile.lock
README.md
azure-pipelines.yml
process.json
setup.py
tox.ini
brewblox_automation/__init__.py
brewblox_automation/__main__.py
brewblox_automation/actions.py
brewblox_automation/api.py
brewblox_automation/conditions.py
brewblox_automation/runner.py
brewblox_automation/sse.py
brewblox_automation/store.py
brewblox_automation/utils.py
brewblox_automation/validation.py
brewblox_automation.egg-info/PKG-INFO
brewblox_automation.egg-info/SOURCES.txt
brewblox_automation.egg-info/dependency_links.txt
brewblox_automation.egg-info/requires.txt
brewblox_automation.egg-info/top_level.txt
config/.gitkeep
docker/.gitignore
docker/localbuild.sh
docker/amd/Dockerfile
docker/arm/Dockerfile
test/__init__.py
test/conftest.py
test/test_actions.py
test/test_api.py
test/test_conditions.py
test/test_main.py
test/test_runner.py
test/test_sse.py
test/test_store.py
test/test_validation.py