Metadata-Version: 2.1
Name: brewblox-automation
Version: 0.1.1.dev35
Summary: UNKNOWN
Home-page: https://github.com/BrewBlox/brewblox-automation/
Author: BrewPi
Author-email: Development@brewpi.com
License: UNKNOWN
Keywords: brewing brewpi brewblox embedded plugin service
Platform: UNKNOWN
Classifier: Development Status :: 4 - Beta
Classifier: License :: OSI Approved :: GNU General Public License (GPL)
Classifier: Programming Language :: Python :: 3.7
Classifier: Intended Audience :: End Users/Desktop
Classifier: Topic :: System :: Hardware
Requires-Python: >=3.7
